[
    {
        "op": "core/text-transform",
        "engineConfig": {
            "facets": [
                {
                    "type": "list",
                    "name": "Portfolio_ID",
                    "expression": "isBlank(value)",
                    "columnName": "Portfolio_ID",
                    "invert": false,
                    "omitBlank": false,
                    "omitError": false,
                    "selection": [
                        {
                            "v": {
                                "v": true,
                                "l": "true"
                            }
                        }
                    ],
                    "selectBlank": false,
                    "selectError": false
                },
                {
                    "type": "list",
                    "name": "temp",
                    "expression": "isBlank(value)",
                    "columnName": "temp",
                    "invert": false,
                    "omitBlank": false,
                    "omitError": false,
                    "selection": [
                        {
                            "v": {
                                "v": false,
                                "l": "false"
                            }
                        }
                    ],
                    "selectBlank": false,
                    "selectError": false
                }
            ],
            "mode": "record-based"
        },
        "columnName": "Portfolio_ID",
        "expression": "grel:cells.temp.value",
        "onError": "keep-original",
        "repeat": false,
        "repeatCount": 10,
        "description": "For records with no ID in ``Portfolio_ID`` but values in ``temp``, add the value from the latter column to the former"
    },
    {
        "op": "core/column-removal",
        "columnName": "temp",
        "description": "Remove column ``temp``"
    }
]